preprocess.py
scraper.py
bookdepositoryscraper-0.1.1.dist-info/LICENSE
bookdepositoryscraper-0.1.1.dist-info/METADATA
bookdepositoryscraper-0.1.1.dist-info/WHEEL
bookdepositoryscraper-0.1.1.dist-info/top_level.txt
bookdepositoryscraper-0.1.1.dist-info/RECORD
