Metadata-Version: 2.1
Name: bookdepositoryscraper
Version: 0.1.1
Summary: Scraper for the Book Depository website
Home-page: https://github.com/adeyinkaoresanya/bookdepositoryscraper
Author: AdeyinkaOresanya
Author-email: adeyinkaoresanya@gmail.com
License: MIT
Keywords: core package
Platform: UNKNOWN
Classifier: Development Status :: 5 - Production/Stable
Classifier: License :: OSI Approved :: MIT License
Classifier: Programming Language :: Python :: 3
Classifier: Operating System :: OS Independent
Requires-Python: >=3.6
